octodns_infomaniak/__init__.py
octodns_infomaniak-0.1.6.dist-info/METADATA
octodns_infomaniak-0.1.6.dist-info/WHEEL
octodns_infomaniak-0.1.6.dist-info/licenses/LICENSE
octodns_infomaniak-0.1.6.dist-info/licenses/LICENSE.en
octodns_infomaniak-0.1.6.dist-info/RECORD
