Metadata-Version: 2.4
Name: octodns-infomaniak
Version: 0.1.6
Summary: Infomaniak provider for octoDNS
Project-URL: Homepage, https://github.com/M0NsTeRRR/octodns-infomaniak
Project-URL: Repository, https://github.com/M0NsTeRRR/octodns-infomaniak
Project-URL: Issues, https://github.com/M0NsTeRRR/octodns-infomaniak/issues
Project-URL: Funding, https://ko-fi.com/ludovicortega
Author-email: Ludovic Ortega <ludovic.ortega@adminafk.fr>
License-File: LICENSE
License-File: LICENSE.en
Keywords: dns,infomaniak,octodns
Classifier: License :: OSI Approved :: CEA CNRS Inria Logiciel Libre License, version 2.1 (CeCILL-2.1)
Classifier: Operating System :: OS Independent
Classifier: Programming Language :: Python
Classifier: Programming Language :: Python :: 3.9
Classifier: Programming Language :: Python :: 3.10
Classifier: Programming Language :: Python :: 3.11
Classifier: Programming Language :: Python :: 3.12
Classifier: Programming Language :: Python :: 3.13
Classifier: Topic :: Utilities
Requires-Python: <4.0.0,>=3.9
Requires-Dist: octodns<2.0.0,>=1.10.0
Requires-Dist: requests>=2.32.0
Provides-Extra: dev
Requires-Dist: pytest-cov~=6.1.0; extra == 'dev'
Requires-Dist: pytest~=8.3.3; extra == 'dev'
Requires-Dist: responses~=0.25.3; extra == 'dev'
Requires-Dist: ruff~=0.11.0; extra == 'dev'
